LICENSE
MANIFEST.in
README.rst
setup.py
sentry_responsible/__init__.py
sentry_responsible/forms.py
sentry_responsible/models.py
sentry_responsible/plugin.py
sentry_responsible.egg-info/PKG-INFO
sentry_responsible.egg-info/SOURCES.txt
sentry_responsible.egg-info/dependency_links.txt
sentry_responsible.egg-info/entry_points.txt
sentry_responsible.egg-info/not-zip-safe
sentry_responsible.egg-info/requires.txt
sentry_responsible.egg-info/top_level.txt
sentry_responsible/locale/de/LC_MESSAGES/django.mo
sentry_responsible/locale/de/LC_MESSAGES/django.po
sentry_responsible/templates/sentry_responsible/widget.html
sentry_responsible/templates/sentry_responsible/emails/notification.txt