Metadata-Version: 1.1
Name: sentry-responsible
Version: 0.3.0
Summary: A Sentry extension which allows you to assign responsibilities for sentry events.
Home-page: https://github.com/andialbrecht/sentry-responsible
Author: Andi Albrecht
Author-email: albrecht.andi@gmail.com
License: BSD
Platform: UNKNOWN
Classifier: Intended Audience :: Developers
Classifier: Intended Audience :: System Administrators
Classifier: Operating System :: OS Independent
Classifier: License :: OSI Approved :: BSD License
Classifier: Programming Language :: Python
Classifier: Framework :: Django
Classifier: Topic :: Software Development
